{"searchCache":{"Recent:diff=-;len=-;str=:0":{"data":"[{\"id\":\"97439592\",\"name\":\"Ton 013\",\"author\":\"OverSpase\",\"difficultyColor\":\"丘뾮"},{\"id\":\"97439591\",\"name\":\"Birth of the Sun\",\"author\":\"CforChuckie\",\"difficultyColor\":\"丘뾮"},{\"id\":\"97439590\",\"name\":\"500 JUMPS\",\"author\":\"roma1000ggg\",\"difficultyColor\":\"丘뾮"},{\"id\":\"97439589\",\"name\":\"500 dollar\",\"author\":\"Spherie\",\"difficultyColor\":\"丘뾮"},{\"id\":\"97439587\",\"name\":\"cdcsp3\",\"author\":\"walterberg\",\"difficultyColor\":\"丘뾮"},{\"id\":\"97439586\",\"name\":\"a block\",\"author\":\"MiPrimeraChamba\",\"difficultyColor\":\"丘뾮"},{\"id\":\"97439585\",\"name\":\"niam\",\"author\":\"Crastilin\",\"difficultyColor\":\"丘뾮"},{\"id\":\"97439584\",\"name\":\"blast fire\",\"author\":\"guisantemat\",\"difficultyColor\":\"丘뾮"},{\"id\":\"97439583\",\"name\":\"3coins1\",\"author\":\"GeorgeIsRandom\",\"difficultyColor\":\"丘뾮"}]","createdAt":1702999923858},"MostLiked:diff=-;len=-;str=:0":{"data":"[{\"id\":\"6508283\",\"name\":\"ReTraY\",\"author\":\"DiMaViKuLov26\",\"difficultyColor\":\"游댯\"},{\"id\":\"4454123\",\"name\":\"Sonar\",\"author\":\"JerkRat\",\"difficultyColor\":\"游댯\"},{\"id\":\"13519\",\"name\":\"The Nightmare\",\"author\":\"Jax\",\"difficultyColor\":\"游댮 (游댯)\"},{\"id\":\"27732941\",\"name\":\"OuterSpace\",\"author\":\"Nicki1202\",\"difficultyColor\":\"游리\"},{\"id\":\"11280109\",\"name\":\"Dark Paradise\",\"author\":\"Roli GD \",\"difficultyColor\":\"游댯\"},{\"id\":\"26618473\",\"name\":\"Promises\",\"author\":\"Adiale\",\"difficultyColor\":\"游댯\"},{\"id\":\"11940\",\"name\":\"Level Easy\",\"author\":\"-\",\"difficultyColor\":\"游릭\"},{\"id\":\"10565740\",\"name\":\"Bloodbath\",\"author\":\"Riot\",\"difficultyColor\":\"游댮 (游댮)\"},{\"id\":\"215705\",\"name\":\"End Of Line\",\"author\":\"PMK\",\"difficultyColor\":\"游릭\"},{\"id\":\"3150\",\"name\":\"auto play area\",\"author\":\"Jax\",\"difficultyColor\":\"游리 (a)\"}]","createdAt":1703032189497},"MostLiked:diff=-;len=-;str=:1":{"data":"[{\"id\":\"28179535\",\"name\":\"Acid Factory\",\"author\":\"pepepromaster69\",\"difficultyColor\":\"游리\"},{\"id\":\"55520\",\"name\":\"THE LIGHTNING ROAD\",\"author\":\"timeless real\",\"difficultyColor\":\"游댮 (游댯)\"},{\"id\":\"4284013\",\"name\":\"Nine Circles\",\"author\":\"Zobros\",\"difficultyColor\":\"游댮 (游리)\"},{\"id\":\"27319926\",\"name\":\"through time\",\"author\":\"Berkoo\",\"difficultyColor\":\"游릭\"},{\"id\":\"1389451\",\"name\":\"dorabaebasic4\",\"author\":\"DORABAE\",\"difficultyColor\":\"游릭\"},{\"id\":\"28255647\",\"name\":\"Chambers\",\"author\":\"SirHadoken\",\"difficultyColor\":\"游릭\"},{\"id\":\"150245\",\"name\":\"Dreamland\",\"author\":\"Scanbrux\",\"difficultyColor\":\"游리\"},{\"id\":\"20635816\",\"name\":\"Amplification\",\"author\":\"Berkoo\",\"difficultyColor\":\"游리\"},{\"id\":\"1642022\",\"name\":\"flappy hexagon\",\"author\":\"Creator Cloud\",\"difficultyColor\":\"游리\"},{\"id\":\"26248615\",\"name\":\"Highscore\",\"author\":\"Danolex\",\"difficultyColor\":\"游릭\"}]","createdAt":1702999936065},"MostLiked:diff=-;len=-;str=:2":{"data":"[{\"id\":\"26949498\",\"name\":\"Spooky Light\",\"author\":\"Serponge\",\"difficultyColor\":\"游릭\"},{\"id\":\"5904109\",\"name\":\"Platinum Adventure\",\"author\":\"Jerry4\",\"difficultyColor\":\"游댮 (游댯)\"},{\"id\":\"29424929\",\"name\":\"Phantom\",\"author\":\"TheRealSalad\",\"difficultyColor\":\"游리\"},{\"id\":\"28225110\",\"name\":\"Shock\",\"author\":\"Danolex\",\"difficultyColor\":\"游\"},{\"id\":\"3543219\",\"name\":\"Speed Racer\",\"author\":\"ZenthicAlpha\",\"difficultyColor\":\"游댮 (游댯)\"},{\"id\":\"27080757\",\"name\":\"Almighty\",\"author\":\"aArbolito\",\"difficultyColor\":\"游리\"},{\"id\":\"18533341\",\"name\":\"Infernal Arena\",\"author\":\"SUOMI\",\"difficultyColor\":\"游릭\"},{\"id\":\"28200611\",\"name\":\"Overture\",\"author\":\"Fault\",\"difficultyColor\":\"游리\"},{\"id\":\"11630859\",\"name\":\"ThE WorLd\",\"author\":\"x8Px\",\"difficultyColor\":\"游댯\"},{\"id\":\"27483789\",\"name\":\"First Race\",\"author\":\"Stamina\",\"difficultyColor\":\"游\"}]","createdAt":1702999936901}}}